narration_xtts2/__init__.py
narration_xtts2/config/config.json
narration_xtts2/TextToSpeak.py
narration_xtts2/utils/__init__.py
narration_xtts2/utils/install_dependents_win11.py
narration_xtts2-1.0.6.dist-info/METADATA
narration_xtts2-1.0.6.dist-info/WHEEL
narration_xtts2-1.0.6.dist-info/RECORD
